Case/__init__.py
Case/Jcx_Case/__init__.py
Case/Jcx_Case/Recharge/Jcx_TopUp_Api.py
Case/Jcx_Case/Recharge/__init__.py
Case/Jcx_Case/Sunscreen_Case/Sunscreen_Api.py
Case/Jcx_Case/Sunscreen_Case/__init__.py
Case/Test_Demo/Ddt_demo.py
Case/Test_Demo/UpDownStuff.py
Case/Test_Demo/ZNcase_01.py
Case/Test_Demo/__init__.py
Config/__init__.py
Data/__init__.py
Data/Body/__init__.py
Data/Body/body_data.py
Data/Headers/__init__.py
Data/Headers/headers_data.py
Data/ID_Card_No/Birthday.py
Data/ID_Card_No/GenArea.py
Data/ID_Card_No/__init__.py
Driver/DoMysql.py
Driver/GenPass.py
Driver/IdentityCard.py
Driver/Sign.py
Driver/__init__.py
Driver/base_request.py
Driver/class.py
Driver/handle_excle.py
Driver/handle_init.py
Driver/hashlib_md5.py
Locust/Locust_Demo.py
Locust/Locust_test.py
Locust/__init__.py
Log/__init__.py
Report/__init__.py
Reptile/__init__.py
Reptile/Requests_Html/Demo.py
Reptile/Requests_Html/__init__.py
Reptile/Requests_Html/c1.py
Reptile/Requests_Html/c2.py
Reptile/Requests_Html/c3.py
Reptile/Requests_Html/c4.py
Reptile/Requests_Html/dict.py
Reptile/Requests_Html/text/__init__.py
Run_Case/Run_case.py
Run_Case/__init__.py
Run_Case/run_main.py
Sunscreen_Api_Test-0.0.7.dist-info/LICENSE
Sunscreen_Api_Test-0.0.7.dist-info/METADATA
Sunscreen_Api_Test-0.0.7.dist-info/WHEEL
Sunscreen_Api_Test-0.0.7.dist-info/top_level.txt
Sunscreen_Api_Test-0.0.7.dist-info/RECORD
