Metadata-Version: 2.1
Name: Sunscreen-Api-Test
Version: 0.0.7
Summary: 接口自动化测试框架
Home-page: https://github.com/yuanjunling/AutomationApiTest.git
Author: yuanjunling
Author-email: 261412489@qq.com
License: UNKNOWN
Platform: UNKNOWN
Classifier: Programming Language :: Python :: 3
Classifier: License :: OSI Approved :: MIT License
Classifier: Operating System :: OS Independent
Requires-Python: >=3.6
